superminhash/__init__.py
superminhash/utlilits.py
test/__init__.py
test/test_superminhash.py
superminhash-0.1.0.dist-info/LICENSE
superminhash-0.1.0.dist-info/METADATA
superminhash-0.1.0.dist-info/WHEEL
superminhash-0.1.0.dist-info/top_level.txt
superminhash-0.1.0.dist-info/RECORD
