Metadata-Version: 2.1
Name: superminhash
Version: 0.1.0
Summary: A SuperMinHash implementation
Home-page: http://github.com/fantasticfears/superminhash
Author: nnnet
License: UNKNOWN
Platform: UNKNOWN
Classifier: Development Status :: 4 - Beta
Classifier: Intended Audience :: Developers
Classifier: Programming Language :: Python :: 3
Requires-Dist: numpy (>=1.10)
Requires-Dist: scikit-learn (>=0.20)
